gurobipy_helper/__init__.c
gurobipy_helper/__init__.py
gurobipy_helper/_coeffs.py
gurobipy_helper/_nonzeros.py
gurobipy_helper/_translate.py
c_gurobipy_helper.cp38-win_amd64.pyd
gurobipy_helper.cp38-win_amd64.pyd
gurobipy_helper/_coeffs.py
gurobipy_helper/_nonzeros.py
gurobipy_helper/_translate.py
gurobipy_helper/__init__.c
gurobipy_helper/__init__.py
gurobipy_helper-0.0.1a10.dist-info/LICENSE
gurobipy_helper-0.0.1a10.dist-info/WHEEL
gurobipy_helper-0.0.1a10.dist-info/METADATA
gurobipy_helper-0.0.1a10.dist-info/RECORD
