Metadata-Version: 2.1
Name: gurobipy-helper
Version: 0.0.1a10
Summary: A library adding some functionality to the Gurobi library.
Home-page: https://github.com/wotzlaff/gurobipy_helper
License: MIT
Author: Nico Strasdat
Author-email: nstrasdat@gmail.com
Classifier: License :: OSI Approved :: MIT License
Classifier: Programming Language :: Python :: 2
Classifier: Programming Language :: Python :: 2.7
Classifier: Programming Language :: Python :: 3
Classifier: Programming Language :: Python :: 3.4
Classifier: Programming Language :: Python :: 3.5
Classifier: Programming Language :: Python :: 3.6
Classifier: Programming Language :: Python :: 3.7
Classifier: Programming Language :: Python :: 3.8
Classifier: Programming Language :: Python :: 3.9
Classifier: Programming Language :: Python :: 3.10
Classifier: Programming Language :: Python :: 3.11
Project-URL: Repository, https://github.com/wotzlaff/gurobipy_helper
